{
    "date": "2023-11-07 03:35:35.390607",
    "time": [
        "0-00",
        "3-00",
        "6-00",
        "9-00",
        "12-00",
        "15-00",
        "18-00",
        "21-00"
    ],
    "temperature": [
        "+10",
        "+10",
        "+9",
        "+9",
        "+10",
        "+9",
        "+9",
        "+8"
    ],
    "windspeed": [
        "2 ",
        "2 ",
        "2 ",
        "2 ",
        "3 ",
        "3 ",
        "2 ",
        "2 "
    ],
    "precipitation": [
        "0",
        "0",
        "0",
        "0",
        "0",
        "0",
        "0",
        "0"
    ],
    "pressure": [],
    "humidity": [
        "86",
        "87",
        "89",
        "88",
        "81",
        "80",
        "78",
        "84"
    ]
}