{
    "date": "2024-05-05 17:35:14.364978",
    "time": [
        "0:-00",
        "3:-00",
        "6:-00",
        "9:-00",
        "12:-00",
        "15:-00",
        "18:-00",
        "21:-00"
    ],
    "temperature": [
        "+8",
        "+6",
        "+7",
        "+15",
        "+18",
        "+19",
        "+15",
        "+14"
    ],
    "windspeed": [
        "0 ",
        "1 ",
        "1 ",
        "4 ",
        "4 ",
        "5 ",
        "3 ",
        "2 "
    ],
    "precipitation": [
        "0",
        "0",
        "0",
        "0",
        "0",
        "0,1",
        "0,2",
        "0"
    ],
    "pressure": [],
    "humidity": [
        "72",
        "81",
        "71",
        "44",
        "39",
        "43",
        "73",
        "41"
    ]
}