{
    "date": "2024-03-14 03:35:24.251694",
    "time": [
        "0:-00",
        "3:-00",
        "6:-00",
        "9:-00",
        "12:-00",
        "15:-00",
        "18:-00",
        "21:-00"
    ],
    "temperature": [
        "−2",
        "−3",
        "−5",
        "−3",
        "+1",
        "+4",
        "+2",
        "+1"
    ],
    "windspeed": [
        "2 ",
        "2 ",
        "2 ",
        "2 ",
        "3 ",
        "3 ",
        "3 ",
        "1 "
    ],
    "precipitation": [
        "0",
        "0",
        "0",
        "0",
        "0",
        "0",
        "0",
        "0"
    ],
    "pressure": [],
    "humidity": [
        "74",
        "78",
        "80",
        "71",
        "54",
        "50",
        "59",
        "74"
    ]
}