{
    "date": "2024-05-13 17:37:20.907850",
    "time": [
        "0:-00",
        "3:-00",
        "6:-00",
        "9:-00",
        "12:-00",
        "15:-00",
        "18:-00",
        "21:-00"
    ],
    "temperature": [
        "+4",
        "+3",
        "+3",
        "+5",
        "+7",
        "+9",
        "+8",
        "+6"
    ],
    "windspeed": [
        "1 ",
        "1 ",
        "0 ",
        "1 ",
        "2 ",
        "1 ",
        "1 ",
        "0 "
    ],
    "precipitation": [
        "0",
        "0",
        "0",
        "0",
        "0",
        "0",
        "0",
        "0"
    ],
    "pressure": [],
    "humidity": [
        "73",
        "77",
        "83",
        "68",
        "56",
        "44",
        "45",
        "58"
    ]
}