{
    "date": "2023-06-22 03:35:29.718429",
    "time": [
        "0-00",
        "3-00",
        "6-00",
        "9-00",
        "12-00",
        "15-00",
        "18-00",
        "21-00"
    ],
    "temperature": [
        "+15",
        "+12",
        "+13",
        "+20",
        "+25",
        "+26",
        "+26",
        "+21"
    ],
    "windspeed": [
        "1 ",
        "1 ",
        "2 ",
        "1 ",
        "2 ",
        "2 ",
        "1 ",
        "1 "
    ],
    "precipitation": [
        "0",
        "0",
        "0",
        "0",
        "0",
        "0",
        "0",
        "0"
    ],
    "pressure": [
        "749",
        "750",
        "750",
        "750",
        "750",
        "748",
        "747",
        "748"
    ],
    "humidity": [
        "65",
        "81",
        "73",
        "51",
        "39",
        "36",
        "37",
        "60"
    ]
}