{
    "date": "2024-05-24 03:35:17.006169",
    "time": [
        "0:-00",
        "3:-00",
        "6:-00",
        "9:-00",
        "12:-00",
        "15:-00",
        "18:-00",
        "21:-00"
    ],
    "temperature": [
        "+13",
        "+11",
        "+10",
        "+14",
        "+18",
        "+20",
        "+20",
        "+14"
    ],
    "windspeed": [
        "1 ",
        "2 ",
        "2 ",
        "3 ",
        "3 ",
        "3 ",
        "2 ",
        "1 "
    ],
    "precipitation": [
        "0",
        "0",
        "0",
        "0",
        "0",
        "0",
        "0",
        "0"
    ],
    "pressure": [],
    "humidity": [
        "47",
        "42",
        "43",
        "45",
        "31",
        "29",
        "29",
        "45"
    ]
}