{
    "date": "2023-07-13 03:41:55.898510",
    "time": [
        "0-00",
        "3-00",
        "6-00",
        "9-00",
        "12-00",
        "15-00",
        "18-00",
        "21-00"
    ],
    "temperature": [
        "+12",
        "+12",
        "+11",
        "+18",
        "+22",
        "+25",
        "+25",
        "+19"
    ],
    "windspeed": [
        "4 ",
        "4 ",
        "1 ",
        "2 ",
        "3 ",
        "4 ",
        "3 ",
        "1 "
    ],
    "precipitation": [
        "0",
        "0",
        "0",
        "0",
        "0",
        "0",
        "0",
        "0"
    ],
    "pressure": [
        "744",
        "744",
        "745",
        "744",
        "744",
        "743",
        "743",
        "743"
    ],
    "humidity": [
        "87",
        "88",
        "86",
        "65",
        "47",
        "37",
        "40",
        "65"
    ]
}